wsinfer_zoo/__init__.py
wsinfer_zoo/__main__.py
wsinfer_zoo/_version.py
wsinfer_zoo/cli.py
wsinfer_zoo/client.py
wsinfer_zoo/py.typed
wsinfer_zoo/schemas/model-config.schema.json
wsinfer_zoo/schemas/wsinfer-zoo-registry.schema.json
wsinfer_zoo-0.6.3.dist-info/LICENSE
wsinfer_zoo-0.6.3.dist-info/METADATA
wsinfer_zoo-0.6.3.dist-info/WHEEL
wsinfer_zoo-0.6.3.dist-info/entry_points.txt
wsinfer_zoo-0.6.3.dist-info/top_level.txt
wsinfer_zoo-0.6.3.dist-info/RECORD
